File.py
Lesson.py
SharePoint.py
__init__.py
schedule_parser_portal_petrocollege-0.0.6.dist-info/LICENSE
schedule_parser_portal_petrocollege-0.0.6.dist-info/METADATA
schedule_parser_portal_petrocollege-0.0.6.dist-info/WHEEL
schedule_parser_portal_petrocollege-0.0.6.dist-info/top_level.txt
schedule_parser_portal_petrocollege-0.0.6.dist-info/RECORD
