Metadata-Version: 2.1
Name: schedule-parser-portal-petrocollege
Version: 0.0.6
Summary: Parser for schedule petrocollege
Author-email: "Andrei V. Berezhkov" <berezhkov.mail@yadndex.ru>
Project-URL: Homepage, https://github.com/a-berezhkov/portal-petrocollege-parser
Project-URL: Bug Tracker, https://github.com/a-berezhkov/portal-petrocollege-parser/issues
Classifier: Programming Language :: Python :: 3
Classifier: License :: OSI Approved :: MIT License
Classifier: Operating System :: OS Independent
Requires-Python: >=3.9
License-File: LICENSE
Requires-Dist: requests (>=2.26.0)
Requires-Dist: requests-ntlm (==1.1.0)
Requires-Dist: openpyxl (==3.0.10)
